ingame/__init__.py
ingame/core.py
ingame/objects.py
ingame-0.4.4.dist-info/licenses/LICENSE
ingame-0.4.4.dist-info/METADATA
ingame-0.4.4.dist-info/WHEEL
ingame-0.4.4.dist-info/top_level.txt
ingame-0.4.4.dist-info/RECORD
