Metadata-Version: 2.4
Name: ingame
Version: 0.4.4
Summary: A window and UI library based on tkinter.
Author-email: Natuworkguy <info@nathannetwork.com>
License: MIT
Project-URL: Homepage, https://github.com/Natuworkguy/InGame
Project-URL: Bug Tracker, https://github.com/Natuworkguy/InGame/issues
Requires-Python: >=3.9.6
License-File: LICENSE
Dynamic: license-file
